Workbook
Name Slicer_category_Cleaned: #N/A

Sheet Shoe_Sales
A1: Date | B1: Product | C1: Product Cleaned | D1: Category | E1: category Cleaned | F1: Color | G1: Brand | H1: Brand Cleaned | I1: Country | J1: Quantity | K1: Payment Type | L1: Selling Price | M1: Cost Price | N1: Revenue | O1: Cost | P1: Profit | Q1: Profit Margin
A2: 46161 | B2: monk straps | C2: Monk Straps | D2: Formal | E2: Formal | F2: Red | G2: Nike | H2: Nike | I2: Uganda | J2: 7 | K2: Bank Transfer | L2: 89 | M2: 47 | N2: 623 | O2: 329 | P2: 294 | Q2: 0.47191011
A3: 46199 | B3: loafers | C3: Loafers | D3: Formal | E3: Formal | F3: Black | G3: nike | H3: Nike | I3: Uganda | J3: 1 | K3: Card | L3: 54 | M3: 28 | N3: 54 | O3: 28 | P3: 26 | Q3: 0.48148148
A4: 46172 | B4: Derby | C4: Derby | D4: FORMAL | E4: Formal | F4: Green | G4: clarks | H4: Clarks | I4: Nigeria | J4: 7 | K4: Bank Transfer | L4: 32 | M4: 14 | N4: 224 | O4: 98 | P4: 126 | Q4: 0.5625
A5: 46214 | B5: boots | C5: Boots | D5: UTILITY | E5: Utility | F5: Black | G5: nike | H5: Nike | I5: Canada | J5: 6 | K5: Bank Transfer | L5: 76 | M5: 39 | N5: 456 | O5: 234 | P5: 222 | Q5: 0.48684211
A6: 46130 | B6: BOOTS | C6: Boots | D6: casual | E6: Casual | F6: Red | G6: CLARKS | H6: Clarks | I6: UK | J6: 6 | K6: Bank Transfer | L6: 76 | M6: 39 | N6: 456 | O6: 234 | P6: 222 | Q6: 0.48684211
A7: 46093 | B7: Canvas | C7: Canvas | D7: Utility | E7: Utility | F7: Blue | G7: NIKE | H7: Nike | I7: Ghana | J7: 6 | K7: Card | L7: 128 | M7: 72 | N7: 768 | O7: 432 | P7: 336 | Q7: 0.4375
A8: 46191 | B8: canvas | C8: Canvas | D8: Formal | E8: Formal | F8: Green | G8: clarks | H8: Clarks | I8: USA | J8: 13 | K8: Cash | L8: 128 | M8: 72 | N8: 1664 | O8: 936 | P8: 728 | Q8: 0.4375
A9: 46212 | B9: monk straps | C9: Monk Straps | D9: Formal | E9: Formal | F9: Brown | G9: timberland | H9: Timberland | I9: USA | J9: 12 | K9: Cash | L9: 89 | M9: 47 | N9: 1068 | O9: 564 | P9: 504 | Q9: 0.47191011
A10: 46038 | B10: Derby | C10: Derby | D10: formal | E10: Formal | F10: Green | G10: clarks | H10: Clarks | I10: Australia | J10: 10 | K10: Cash | L10: 32 | M10: 14 | N10: 320 | O10: 140 | P10: 180 | Q10: 0.5625
A11: 46182 | B11: OXFORD | C11: Oxford | D11: Formal | E11: Formal | F11: Black | G11: clarks | H11: Clarks | I11: Cyprus | J11: 15 | K11: Mobile Money | L11: 105 | M11: 58 | N11: 1575 | O11: 870 | P11: 705 | Q11: 0.44761905
A12: 46132 | B12: BOOTS | C12: Boots | D12: Formal | E12: Formal | F12: Brown | G12: Clarks | H12: Clarks | I12: India | J12: 8 | K12: Bank Transfer | L12: 76 | M12: 39 | N12: 608 | O12: 312 | P12: 296 | Q12: 0.48684211
A13: 46097 | B13: loafers | C13: Loafers | D13: casual | E13: Casual | F13: Green | G13: Clarks | H13: Clarks | I13: Australia | J13: 9 | K13: Cash | L13: 54 | M13: 28 | N13: 486 | O13: 252 | P13: 234 | Q13: 0.48148148
... A501: 46218 | B501: Derby | C501: Derby | D501: casual | E501: Casual | F501: Red | G501: CLARKS | H501: Clarks | I501: Germany | J501: 4 | K501: Bank Transfer | L501: 32 | M501: 14 | N501: 128 | O501: 56 | P501: 72 | Q501: 0.5625

Sheet Pivot Table
H1: Revenue by Category | M1: Revenue by Product | X1: Revenue by Category | AF1: Revenue by Brand | AN1: Profit by country
A2: Total Revenue | B2: Total Cost | C2: Total Profit | D2: Total Profit Margin | E2: Quantity Sold | I2: Month | J2: Total Revenue | N2: Product | O2: Total Revenue | X2: Category | Y2: Total Revenue | AF2: Brand | AG2: Total Revenue | AN2: Country | AO2: Total Profit | AP2: Total Revenue | AY2: Profit by country | BK2: Revenue by Brand
A3: 135952 | B3: 74027 | C3: 61925 | D3: 0.4717589 | E3: 1504 | I3: Jan | J3: 15969 | N3: Boots | O3: 15352 | X3: Casual | Y3: 82917 | AF3: Clarks | AG3: 49122 | AN3: Albania | AO3: 2600 | AP3: 5699 | AY3: Country | AZ3: Total Revenue | BK3: Payment Type | BL3: Count of Payment Type
I4: Feb | J4: 15129 | N4: Brogues | O4: 23968 | X4: Open | Y4: 53035 | AF4: Nike | AG4: 21242 | AN4: Australia | AO4: 2204 | AP4: 4942 | AY4: Ghana | AZ4: 12161 | BK4: Bank Transfer | BL4: 48
I5: Mar | J5: 19014 | N5: Canvas | O5: 28160 | X5: Grand Total | Y5: 135952 | AF5: Steve Madden | AG5: 14062 | AN5: Canada | AO5: 3426 | AP5: 7609 | AY5: Uganda | AZ5: 13616 | BK5: Card | BL5: 54
I6: Apr | J6: 16132 | N6: Derby | O6: 6528 | AF6: Timberland | AG6: 19559 | AN6: Cyprus | AO6: 3759 | AP6: 8230 | AY6: UK | AZ6: 15657 | BK6: Cash | BL6: 51
I7: May | J7: 15486 | N7: Loafers | O7: 7344 | AF7: Zara | AG7: 31967 | AN7: Germany | AO7: 2330 | AP7: 5248 | AY7: USA | AZ7: 12806 | BK7: Mobile Money | BL7: 41
I8: Jun | J8: 28993 | N8: Monk Straps | O8: 16821 | AF8: Grand Total | AG8: 135952 | AN8: Ghana | AO8: 5500 | AP8: 12161 | AY8: Zimbabwe | AZ8: 13452 | BK8: Grand Total | BL8: 194
I9: Jul | J9: 17765 | N9: Oxford | O9: 19215 | AN9: India | AO9: 5427 | AP9: 11802 | AY9: Grand Total | AZ9: 67692
I10: Aug | J10: 7464 | N10: Slippers | O10: 18564 | AN10: Kenya | AO10: 2922 | AP10: 6370
I11: Grand Total | J11: 135952 | N11: Grand Total | O11: 135952 | AN11: Nigeria | AO11: 3436 | AP11: 7345
AN12: Philippines | AO12: 4940 | AP12: 11015
AN13: Uganda | AO13: 6148 | AP13: 13616
AN14: UK | AO14: 7261 | AP14: 15657
AN15: USA | AO15: 5831 | AP15: 12806
AN16: Zimbabwe | AO16: 6141 | AP16: 13452
AN17: Grand Total | AO17: 61925 | AP17: 135952

Sheet Dashboard

Sheet Shoe Sales
A1: Date | B1: Product | C1: Product Cleaned | D1: Category | E1: category Cleaned | F1: Color | G1: Brand | H1: Brand Cleaned | I1: Country | J1: Quantity | K1: Payment Type | L1: Selling Price | M1: Cost Price | N1: Revenue | O1: Cost | P1: Profit | Q1: Profit Margin
A2: 46161 | B2: monk straps | C2: =TRIM(PROPER(B2)) -> Monk Straps | D2: Formal | E2: =PROPER(D2) -> Formal | F2: Red | G2: Nike | H2: =PROPER(Shoe_Sales[[#This Row],[Brand]]) -> Nike | I2: Uganda | J2: 7 | K2: Bank Transfer | L2: =VLOOKUP(Shoe_Sales[[#This Row],[Product Cleaned]],Price!$A$2:$C$9,2,FALSE) -> 89 | M2: =VLOOKUP(Shoe_Sales[[#This Row],[Product Cleaned]],Price!$A$2:$C$9,3,0) -> 47 | N2: =(Shoe_Sales[[#This Row],[Quantity]]*Shoe_Sales[[#This Row],[Selling Price]]) -> 623 | O2: =(Shoe_Sales[[#This Row],[Quantity]]*Shoe_Sales[[#This Row],[Cost Price]]) -> 329 | P2: =(Shoe_Sales[[#This Row],[Revenue]]-Shoe_Sales[[#This Row],[Cost]]) -> 294 | Q2: =(Shoe_Sales[[#This Row],[Profit]]/Shoe_Sales[[#This Row],[Revenue]]) -> 0.47191011
A3: 46199 | B3: loafers | C3: =TRIM(PROPER(B3)) -> Loafers | D3: Formal | E3: =PROPER(D3) -> Formal | F3: Black | G3: nike | H3: =PROPER(Shoe_Sales[[#This Row],[Brand]]) -> Nike | I3: Uganda | J3: 1 | K3: Card | L3: =VLOOKUP(Shoe_Sales[[#This Row],[Product Cleaned]],Price!$A$2:$C$9,2,FALSE) -> 54 | M3: =VLOOKUP(Shoe_Sales[[#This Row],[Product Cleaned]],Price!$A$2:$C$9,3,0) -> 28 | N3: =(Shoe_Sales[[#This Row],[Quantity]]*Shoe_Sales[[#This Row],[Selling Price]]) -> 54 | O3: =(Shoe_Sales[[#This Row],[Quantity]]*Shoe_Sales[[#This Row],[Cost Price]]) -> 28 | P3: =(Shoe_Sales[[#This Row],[Revenue]]-Shoe_Sales[[#This Row],[Cost]]) -> 26 | Q3: =(Shoe_Sales[[#This Row],[Profit]]/Shoe_Sales[[#This Row],[Revenue]]) -> 0.48148148
A4: 46172 | B4: Derby | C4: =TRIM(PROPER(B4)) -> Derby | D4: FORMAL | E4: =PROPER(D4) -> Formal | F4: Green | G4: clarks | H4: =PROPER(Shoe_Sales[[#This Row],[Brand]]) -> Clarks | I4: Nigeria | J4: 7 | K4: Bank Transfer | L4: =VLOOKUP(Shoe_Sales[[#This Row],[Product Cleaned]],Price!$A$2:$C$9,2,FALSE) -> 32 | M4: =VLOOKUP(Shoe_Sales[[#This Row],[Product Cleaned]],Price!$A$2:$C$9,3,0) -> 14 | N4: =(Shoe_Sales[[#This Row],[Quantity]]*Shoe_Sales[[#This Row],[Selling Price]]) -> 224 | O4: =(Shoe_Sales[[#This Row],[Quantity]]*Shoe_Sales[[#This Row],[Cost Price]]) -> 98 | P4: =(Shoe_Sales[[#This Row],[Revenue]]-Shoe_Sales[[#This Row],[Cost]]) -> 126 | Q4: =(Shoe_Sales[[#This Row],[Profit]]/Shoe_Sales[[#This Row],[Revenue]]) -> 0.5625
A5: 46214 | B5: boots | C5: =TRIM(PROPER(B5)) -> Boots | D5: UTILITY | E5: =PROPER(D5) -> Utility | F5: Black | G5: nike | H5: =PROPER(Shoe_Sales[[#This Row],[Brand]]) -> Nike | I5: Canada | J5: 6 | K5: Bank Transfer | L5: =VLOOKUP(Shoe_Sales[[#This Row],[Product Cleaned]],Price!$A$2:$C$9,2,FALSE) -> 76 | M5: =VLOOKUP(Shoe_Sales[[#This Row],[Product Cleaned]],Price!$A$2:$C$9,3,0) -> 39 | N5: =(Shoe_Sales[[#This Row],[Quantity]]*Shoe_Sales[[#This Row],[Selling Price]]) -> 456 | O5: =(Shoe_Sales[[#This Row],[Quantity]]*Shoe_Sales[[#This Row],[Cost Price]]) -> 234 | P5: =(Shoe_Sales[[#This Row],[Revenue]]-Shoe_Sales[[#This Row],[Cost]]) -> 222 | Q5: =(Shoe_Sales[[#This Row],[Profit]]/Shoe_Sales[[#This Row],[Revenue]]) -> 0.48684211
A6: 46130 | B6: BOOTS | C6: =TRIM(PROPER(B6)) -> Boots | D6: casual | E6: =PROPER(D6) -> Casual | F6: Red | G6: CLARKS | H6: =PROPER(Shoe_Sales[[#This Row],[Brand]]) -> Clarks | I6: UK | J6: 6 | K6: Bank Transfer | L6: =VLOOKUP(Shoe_Sales[[#This Row],[Product Cleaned]],Price!$A$2:$C$9,2,FALSE) -> 76 | M6: =VLOOKUP(Shoe_Sales[[#This Row],[Product Cleaned]],Price!$A$2:$C$9,3,0) -> 39 | N6: =(Shoe_Sales[[#This Row],[Quantity]]*Shoe_Sales[[#This Row],[Selling Price]]) -> 456 | O6: =(Shoe_Sales[[#This Row],[Quantity]]*Shoe_Sales[[#This Row],[Cost Price]]) -> 234 | P6: =(Shoe_Sales[[#This Row],[Revenue]]-Shoe_Sales[[#This Row],[Cost]]) -> 222 | Q6: =(Shoe_Sales[[#This Row],[Profit]]/Shoe_Sales[[#This Row],[Revenue]]) -> 0.48684211
A7: 46093 | B7: Canvas | C7: =TRIM(PROPER(B7)) -> Canvas | D7: Utility | E7: =PROPER(D7) -> Utility | F7: Blue | G7: NIKE | H7: =PROPER(Shoe_Sales[[#This Row],[Brand]]) -> Nike | I7: Ghana | J7: 6 | K7: Card | L7: =VLOOKUP(Shoe_Sales[[#This Row],[Product Cleaned]],Price!$A$2:$C$9,2,FALSE) -> 128 | M7: =VLOOKUP(Shoe_Sales[[#This Row],[Product Cleaned]],Price!$A$2:$C$9,3,0) -> 72 | N7: =(Shoe_Sales[[#This Row],[Quantity]]*Shoe_Sales[[#This Row],[Selling Price]]) -> 768 | O7: =(Shoe_Sales[[#This Row],[Quantity]]*Shoe_Sales[[#This Row],[Cost Price]]) -> 432 | P7: =(Shoe_Sales[[#This Row],[Revenue]]-Shoe_Sales[[#This Row],[Cost]]) -> 336 | Q7: =(Shoe_Sales[[#This Row],[Profit]]/Shoe_Sales[[#This Row],[Revenue]]) -> 0.4375
A8: 46191 | B8: canvas | C8: =TRIM(PROPER(B8)) -> Canvas | D8: Formal | E8: =PROPER(D8) -> Formal | F8: Green | G8: clarks | H8: =PROPER(Shoe_Sales[[#This Row],[Brand]]) -> Clarks | I8: USA | J8: 13 | K8: Cash | L8: =VLOOKUP(Shoe_Sales[[#This Row],[Product Cleaned]],Price!$A$2:$C$9,2,FALSE) -> 128 | M8: =VLOOKUP(Shoe_Sales[[#This Row],[Product Cleaned]],Price!$A$2:$C$9,3,0) -> 72 | N8: =(Shoe_Sales[[#This Row],[Quantity]]*Shoe_Sales[[#This Row],[Selling Price]]) -> 1664 | O8: =(Shoe_Sales[[#This Row],[Quantity]]*Shoe_Sales[[#This Row],[Cost Price]]) -> 936 | P8: =(Shoe_Sales[[#This Row],[Revenue]]-Shoe_Sales[[#This Row],[Cost]]) -> 728 | Q8: =(Shoe_Sales[[#This Row],[Profit]]/Shoe_Sales[[#This Row],[Revenue]]) -> 0.4375
A9: 46212 | B9: monk straps | C9: =TRIM(PROPER(B9)) -> Monk Straps | D9: Formal | E9: =PROPER(D9) -> Formal | F9: Brown | G9: timberland | H9: =PROPER(Shoe_Sales[[#This Row],[Brand]]) -> Timberland | I9: USA | J9: 12 | K9: Cash | L9: =VLOOKUP(Shoe_Sales[[#This Row],[Product Cleaned]],Price!$A$2:$C$9,2,FALSE) -> 89 | M9: =VLOOKUP(Shoe_Sales[[#This Row],[Product Cleaned]],Price!$A$2:$C$9,3,0) -> 47 | N9: =(Shoe_Sales[[#This Row],[Quantity]]*Shoe_Sales[[#This Row],[Selling Price]]) -> 1068 | O9: =(Shoe_Sales[[#This Row],[Quantity]]*Shoe_Sales[[#This Row],[Cost Price]]) -> 564 | P9: =(Shoe_Sales[[#This Row],[Revenue]]-Shoe_Sales[[#This Row],[Cost]]) -> 504 | Q9: =(Shoe_Sales[[#This Row],[Profit]]/Shoe_Sales[[#This Row],[Revenue]]) -> 0.47191011
A10: 46038 | B10: Derby | C10: =TRIM(PROPER(B10)) -> Derby | D10: formal | E10: =PROPER(D10) -> Formal | F10: Green | G10: clarks | H10: =PROPER(Shoe_Sales[[#This Row],[Brand]]) -> Clarks | I10: Australia | J10: 10 | K10: Cash | L10: =VLOOKUP(Shoe_Sales[[#This Row],[Product Cleaned]],Price!$A$2:$C$9,2,FALSE) -> 32 | M10: =VLOOKUP(Shoe_Sales[[#This Row],[Product Cleaned]],Price!$A$2:$C$9,3,0) -> 14 | N10: =(Shoe_Sales[[#This Row],[Quantity]]*Shoe_Sales[[#This Row],[Selling Price]]) -> 320 | O10: =(Shoe_Sales[[#This Row],[Quantity]]*Shoe_Sales[[#This Row],[Cost Price]]) -> 140 | P10: =(Shoe_Sales[[#This Row],[Revenue]]-Shoe_Sales[[#This Row],[Cost]]) -> 180 | Q10: =(Shoe_Sales[[#This Row],[Profit]]/Shoe_Sales[[#This Row],[Revenue]]) -> 0.5625
A11: 46182 | B11: OXFORD | C11: =TRIM(PROPER(B11)) -> Oxford | D11: Formal | E11: =PROPER(D11) -> Formal | F11: Black | G11: clarks | H11: =PROPER(Shoe_Sales[[#This Row],[Brand]]) -> Clarks | I11: Cyprus | J11: 15 | K11: Mobile Money | L11: =VLOOKUP(Shoe_Sales[[#This Row],[Product Cleaned]],Price!$A$2:$C$9,2,FALSE) -> 105 | M11: =VLOOKUP(Shoe_Sales[[#This Row],[Product Cleaned]],Price!$A$2:$C$9,3,0) -> 58 | N11: =(Shoe_Sales[[#This Row],[Quantity]]*Shoe_Sales[[#This Row],[Selling Price]]) -> 1575 | O11: =(Shoe_Sales[[#This Row],[Quantity]]*Shoe_Sales[[#This Row],[Cost Price]]) -> 870 | P11: =(Shoe_Sales[[#This Row],[Revenue]]-Shoe_Sales[[#This Row],[Cost]]) -> 705 | Q11: =(Shoe_Sales[[#This Row],[Profit]]/Shoe_Sales[[#This Row],[Revenue]]) -> 0.44761905
A12: 46132 | B12: BOOTS | C12: =TRIM(PROPER(B12)) -> Boots | D12: Formal | E12: =PROPER(D12) -> Formal | F12: Brown | G12: Clarks | H12: =PROPER(Shoe_Sales[[#This Row],[Brand]]) -> Clarks | I12: India | J12: 8 | K12: Bank Transfer | L12: =VLOOKUP(Shoe_Sales[[#This Row],[Product Cleaned]],Price!$A$2:$C$9,2,FALSE) -> 76 | M12: =VLOOKUP(Shoe_Sales[[#This Row],[Product Cleaned]],Price!$A$2:$C$9,3,0) -> 39 | N12: =(Shoe_Sales[[#This Row],[Quantity]]*Shoe_Sales[[#This Row],[Selling Price]]) -> 608 | O12: =(Shoe_Sales[[#This Row],[Quantity]]*Shoe_Sales[[#This Row],[Cost Price]]) -> 312 | P12: =(Shoe_Sales[[#This Row],[Revenue]]-Shoe_Sales[[#This Row],[Cost]]) -> 296 | Q12: =(Shoe_Sales[[#This Row],[Profit]]/Shoe_Sales[[#This Row],[Revenue]]) -> 0.48684211
A13: 46097 | B13: loafers | C13: =TRIM(PROPER(B13)) -> Loafers | D13: casual | E13: =PROPER(D13) -> Casual | F13: Green | G13: Clarks | H13: =PROPER(Shoe_Sales[[#This Row],[Brand]]) -> Clarks | I13: Australia | J13: 9 | K13: Cash | L13: =VLOOKUP(Shoe_Sales[[#This Row],[Product Cleaned]],Price!$A$2:$C$9,2,FALSE) -> 54 | M13: =VLOOKUP(Shoe_Sales[[#This Row],[Product Cleaned]],Price!$A$2:$C$9,3,0) -> 28 | N13: =(Shoe_Sales[[#This Row],[Quantity]]*Shoe_Sales[[#This Row],[Selling Price]]) -> 486 | O13: =(Shoe_Sales[[#This Row],[Quantity]]*Shoe_Sales[[#This Row],[Cost Price]]) -> 252 | P13: =(Shoe_Sales[[#This Row],[Revenue]]-Shoe_Sales[[#This Row],[Cost]]) -> 234 | Q13: =(Shoe_Sales[[#This Row],[Profit]]/Shoe_Sales[[#This Row],[Revenue]]) -> 0.48148148
... A501: 46218 | B501: Derby | C501: =TRIM(PROPER(B501)) -> Derby | D501: casual | E501: =PROPER(D501) -> Casual | F501: Red | G501: CLARKS | H501: =PROPER(Shoe_Sales[[#This Row],[Brand]]) -> Clarks | I501: Germany | J501: 4 | K501: Bank Transfer | L501: =VLOOKUP(Shoe_Sales[[#This Row],[Product Cleaned]],Price!$A$2:$C$9,2,FALSE) -> 32 | M501: =VLOOKUP(Shoe_Sales[[#This Row],[Product Cleaned]],Price!$A$2:$C$9,3,0) -> 14 | N501: =(Shoe_Sales[[#This Row],[Quantity]]*Shoe_Sales[[#This Row],[Selling Price]]) -> 128 | O501: =(Shoe_Sales[[#This Row],[Quantity]]*Shoe_Sales[[#This Row],[Cost Price]]) -> 56 | P501: =(Shoe_Sales[[#This Row],[Revenue]]-Shoe_Sales[[#This Row],[Cost]]) -> 72 | Q501: =(Shoe_Sales[[#This Row],[Profit]]/Shoe_Sales[[#This Row],[Revenue]]) -> 0.5625

Sheet Price
A1: Product | B1: Price | C1: Cost
A2: Monk Straps | B2: 89 | C2: 47
A3: Loafers | B3: 54 | C3: 28
A4: Derby | B4: 32 | C4: 14
A5: Boots | B5: 76 | C5: 39
A6: Canvas | B6: 128 | C6: 72
A7: Oxford | B7: 105 | C7: 58
A8: Brogues | B8: 112 | C8: 64
A9: Slippers | B9: 119 | C9: 67

Sheet Business questions
A1: Business Questions:
A3: 1 | B3: How is the business performing overall?
A4: 2 | B4: How have revenue and profit changed over time?
A5: 3 | B5: Which products are driving sales?
A6: 4 | B6: Which products are driving profitability?
A7: 5 | B7: Which categories and brands perform best?
A8: 6 | B8: Which countries contribute the most to the business?
A9: 7 | B9: What purchasing patterns can we identify from payment method and product preferences?
A10: 8 | B10: What actions should management take based on the findings?
